LICENSE
MANIFEST.in
README.md
pyproject.toml
setup.py
bindings/bindings.cpp
mweralign/__init__.py
mweralign/mweralign.py
mweralign/segmenter.py
mweralign.egg-info/PKG-INFO
mweralign.egg-info/SOURCES.txt
mweralign.egg-info/dependency_links.txt
mweralign.egg-info/entry_points.txt
mweralign.egg-info/not-zip-safe
mweralign.egg-info/requires.txt
mweralign.egg-info/top_level.txt
mweralign/tests/test_mweralign.py
mweralign/tests/test_segmenter.py
src/main.cc
src/mwerAlign.cc
src/mwerAlign.hh