Metadata-Version: 2.4
Name: mweralign
Version: 1.0.1
Summary: Minimum Word Error Rate Alignment for speech recognition evaluation
Author-email: Matt Post <mattpost@microsoft.com>
License-Expression: GPL-3.0-or-later
Classifier: Development Status :: 3 - Alpha
Classifier: Intended Audience :: Science/Research
Classifier: Programming Language :: Python :: 3
Classifier: Programming Language :: C++
Requires-Python: >=3.10
License-File: LICENSE
Requires-Dist: sentencepiece
Provides-Extra: dev
Requires-Dist: pytest; extra == "dev"
Requires-Dist: black; extra == "dev"
Requires-Dist: flake8; extra == "dev"
Dynamic: license-file
